yolo_dataset_redactor/__init__.py
yolo_dataset_redactor/base/__init__.py
yolo_dataset_redactor/base/file_editor.py
yolo_dataset_redactor/base/file_finder.py
yolo_dataset_redactor/image/__init__.py
yolo_dataset_redactor/image/base.py
yolo_dataset_redactor/image/image.py
yolo_dataset_redactor/image/images.py
yolo_dataset_redactor/label/__init__.py
yolo_dataset_redactor/label/base.py
yolo_dataset_redactor/label/label.py
yolo_dataset_redactor/label/labels.py
yolo_dataset_redactor/video/__init__.py
yolo_dataset_redactor/video/base.py
yolo_dataset_redactor/video/video.py
yolo_dataset_redactor/video/videos.py
yolo_dataset_redactor-0.2.1.dist-info/licenses/License.md
yolo_dataset_redactor-0.2.1.dist-info/METADATA
yolo_dataset_redactor-0.2.1.dist-info/WHEEL
yolo_dataset_redactor-0.2.1.dist-info/top_level.txt
yolo_dataset_redactor-0.2.1.dist-info/RECORD
