Metadata-Version: 2.4
Name: yolo_dataset_redactor
Version: 0.2.1
Author-email: lexter0705 <lexter0705@gmail.com>
Project-URL: repository, https://github.com/lexter0705/yolo_dataset_redactor
Classifier: Programming Language :: Python :: 3
Classifier: License :: OSI Approved :: MIT License
Classifier: Operating System :: OS Independent
Requires-Python: >=3.12.0
License-File: License.md
Requires-Dist: opencv-python>=4.10
Dynamic: license-file
